{"version":2,"kind":"Notebook","sha256":"97dc4c286bba315786ba3ad7ad92fb978aaa9ad6a354332371c737eda807d3db","slug":"physical.reliefs","location":"/physical/23-Reliefs.ipynb","dependencies":[],"frontmatter":{"title":"23-Reliefs","content_includes_title":false,"kernelspec":{"name":"python3","display_name":"jupiterbook","language":"python"},"authors":[{"nameParsed":{"literal":"Clint Guymon","given":"Clint","family":"Guymon"},"name":"Clint Guymon","id":"contributors-myst-generated-uid-0"},{"nameParsed":{"literal":"Brigham Young University","given":"Brigham Young","family":"University"},"name":"Brigham Young University","id":"contributors-myst-generated-uid-1"}],"date":"2025-12-25","github":"https://github.com/clint-bg/safetyinjc","keywords":["Process Safety","Chemical Engineering","Risk Assessment"],"numbering":{"title":{"offset":1}},"edit_url":"https://github.com/clint-bg/safetyinjc/blob/main/physical/23-Reliefs.ipynb","thumbnail":"/9cc043006bc6965018b98bd3436dbf31.png","thumbnailOptimized":"/9cc043006bc6965018b98bd3436dbf31.webp","exports":[{"format":"ipynb","filename":"23-Reliefs.ipynb","url":"/23-Reliefs-0fc3f4b50a0f7ff39cb6464650ebd6a0.ipynb"}]},"widgets":{},"mdast":{"type":"root","children":[{"type":"block","kind":"notebook-content","children":[{"type":"paragraph","position":{"start":{"line":1,"column":1},"end":{"line":1,"column":1}},"children":[{"type":"text","value":"Learning Objectives:","position":{"start":{"line":1,"column":1},"end":{"line":1,"column":1}},"key":"mFSln6s1th"}],"key":"RRb8eIIbQ9"},{"type":"list","ordered":false,"spread":false,"position":{"start":{"line":2,"column":1},"end":{"line":4,"column":1}},"children":[{"type":"listItem","spread":true,"position":{"start":{"line":2,"column":1},"end":{"line":2,"column":1}},"children":[{"type":"text","value":"Understand the importance of ","position":{"start":{"line":2,"column":1},"end":{"line":2,"column":1}},"key":"pQEulT1BTJ"},{"type":"strong","position":{"start":{"line":2,"column":1},"end":{"line":2,"column":1}},"children":[{"type":"text","value":"pressure protection","position":{"start":{"line":2,"column":1},"end":{"line":2,"column":1}},"key":"TJPmz4Ry5I"}],"key":"q0TibZPdWy"}],"key":"yFczayFszA"},{"type":"listItem","spread":true,"position":{"start":{"line":3,"column":1},"end":{"line":3,"column":1}},"children":[{"type":"text","value":"Identify and understand the different ","position":{"start":{"line":3,"column":1},"end":{"line":3,"column":1}},"key":"o8OzhSdIoq"},{"type":"strong","position":{"start":{"line":3,"column":1},"end":{"line":3,"column":1}},"children":[{"type":"text","value":"types of pressure protection devices","position":{"start":{"line":3,"column":1},"end":{"line":3,"column":1}},"key":"lnyk52smMI"}],"key":"GH5tAA4Z2s"}],"key":"Jptbe8tXJ0"},{"type":"listItem","spread":true,"position":{"start":{"line":4,"column":1},"end":{"line":4,"column":1}},"children":[{"type":"text","value":"Understand ","position":{"start":{"line":4,"column":1},"end":{"line":4,"column":1}},"key":"UYTZFbxSLI"},{"type":"strong","position":{"start":{"line":4,"column":1},"end":{"line":4,"column":1}},"children":[{"type":"text","value":"where and why","position":{"start":{"line":4,"column":1},"end":{"line":4,"column":1}},"key":"CvuNDC8sdt"}],"key":"xDQyFbSkp5"},{"type":"text","value":" pressure protection devices are used","position":{"start":{"line":4,"column":1},"end":{"line":4,"column":1}},"key":"ELCVTPyfrs"}],"key":"uA8jJCzqul"}],"key":"Ke457uv6CJ"}],"key":"C9vK8WeKwq"},{"type":"block","kind":"notebook-content","children":[{"type":"heading","depth":2,"position":{"start":{"line":1,"column":1},"end":{"line":1,"column":1}},"children":[{"type":"text","value":"Pressure Protection","position":{"start":{"line":1,"column":1},"end":{"line":1,"column":1}},"key":"IYZKFqFlc0"}],"identifier":"pressure-protection","label":"Pressure Protection","html_id":"pressure-protection","implicit":true,"key":"n7HEStULOm"}],"key":"EK3tZCcXkt"},{"type":"block","kind":"notebook-content","children":[{"type":"image","url":"/9cc043006bc6965018b98bd3436dbf31.png","width":500,"key":"CwINTy5dv9","urlSource":"https://github.com/clint-bg/safetyinjc/blob/main/physical/supportfiles/reactor.png?raw=true","urlOptimized":"/9cc043006bc6965018b98bd3436dbf31.webp"},{"type":"paragraph","position":{"start":{"line":3,"column":1},"end":{"line":3,"column":1}},"children":[{"type":"emphasis","position":{"start":{"line":3,"column":1},"end":{"line":3,"column":1}},"children":[{"type":"text","value":"AI Generated Image of a Reactor","position":{"start":{"line":3,"column":1},"end":{"line":3,"column":1}},"key":"bnQbeUD1TF"}],"key":"JT5oKfGETv"}],"key":"fdzm1diT3s"}],"key":"hyvHT6b5U9"},{"type":"block","kind":"notebook-content","children":[{"type":"paragraph","position":{"start":{"line":1,"column":1},"end":{"line":1,"column":1}},"children":[{"type":"text","value":"What would be the consequences if the reactor in the image above were to over-pressurize?","position":{"start":{"line":1,"column":1},"end":{"line":1,"column":1}},"key":"nci4Xa05wi"}],"key":"RABNMXB2xS"},{"type":"list","ordered":false,"spread":false,"position":{"start":{"line":2,"column":1},"end":{"line":4,"column":1}},"children":[{"type":"listItem","spread":true,"position":{"start":{"line":2,"column":1},"end":{"line":2,"column":1}},"children":[{"type":"text","value":"The reactor could ","position":{"start":{"line":2,"column":1},"end":{"line":2,"column":1}},"key":"NdUHuaRn6D"},{"type":"strong","position":{"start":{"line":2,"column":1},"end":{"line":2,"column":1}},"children":[{"type":"text","value":"explode","position":{"start":{"line":2,"column":1},"end":{"line":2,"column":1}},"key":"PWgJDhsidP"}],"key":"Em7oZ09dtt"},{"type":"text","value":", causing damage to the plant and surrounding area","position":{"start":{"line":2,"column":1},"end":{"line":2,"column":1}},"key":"c9iVY2DNvu"}],"key":"DWXIjwg4Ft"},{"type":"listItem","spread":true,"position":{"start":{"line":3,"column":1},"end":{"line":3,"column":1}},"children":[{"type":"text","value":"The reactor could ","position":{"start":{"line":3,"column":1},"end":{"line":3,"column":1}},"key":"Xbcxg0Oxzr"},{"type":"strong","position":{"start":{"line":3,"column":1},"end":{"line":3,"column":1}},"children":[{"type":"text","value":"release hazardous chemicals into the environment","position":{"start":{"line":3,"column":1},"end":{"line":3,"column":1}},"key":"r18LpVECdW"}],"key":"LO3aF4Z2TT"}],"key":"gQeqcOImhE"},{"type":"listItem","spread":true,"position":{"start":{"line":4,"column":1},"end":{"line":4,"column":1}},"children":[{"type":"text","value":"The reactor could ","position":{"start":{"line":4,"column":1},"end":{"line":4,"column":1}},"key":"BXZgW43ZiY"},{"type":"strong","position":{"start":{"line":4,"column":1},"end":{"line":4,"column":1}},"children":[{"type":"text","value":"release hazardous chemicals into the plant","position":{"start":{"line":4,"column":1},"end":{"line":4,"column":1}},"key":"oFMVe36uCH"}],"key":"JI0bDZe8GL"},{"type":"text","value":", causing harm to personnel","position":{"start":{"line":4,"column":1},"end":{"line":4,"column":1}},"key":"j5s4u238rV"}],"key":"frlPXYFdKR"}],"key":"ahGoQXXXFm"}],"key":"XynB0HSkzh"},{"type":"block","kind":"notebook-content","children":[{"type":"paragraph","position":{"start":{"line":1,"column":1},"end":{"line":1,"column":1}},"children":[{"type":"text","value":"Explosion approximate consequences:","position":{"start":{"line":1,"column":1},"end":{"line":1,"column":1}},"key":"uWlvTzdmQb"}],"key":"uOdBQNhluy"}],"key":"IGrB0MHeDw"},{"type":"block","kind":"notebook-code","children":[{"type":"code","lang":"python","executable":true,"value":"#Potential energy from exploding reactor\nReactorVolume = 50 #m^3 (13,200 gallons)\nVoidFraction = 0.67 #67% void fraction\nContents = 'Acetone'\nBurstPressure = 10 #bar\nContentMass = ReactorVolume * (1 - VoidFraction) * 785 #kg/m^3, Acetone density estimate\nCombustionHeat = 30.819e6 #J/kg: 1790 kJ/mol, molecular weight 58.08 g/mol","key":"CF9gPZeyDN"},{"type":"output","id":"_NIxPlFcgtQISYKXAWySt","data":[],"key":"u6I1ccAWok"}],"key":"Dz4uhyy3eX"},{"type":"block","kind":"notebook-code","children":[{"type":"code","lang":"python","executable":true,"value":"#Energy from bursting reactor scales with burst pressure and void volume:\nBurstEnergy = BurstPressure * ReactorVolume * 1e5/(1.4-1)*(1-1/BurstPressure)**((1.4-1)/1.4) #Joules\nprint('BurstEnergy, MJ: ', BurstEnergy/1e6)\nCombustionEnergy = ContentMass * CombustionHeat #Joules\nprint(f'CombustionEnergy, MJ: {CombustionEnergy/1e6:.2f}')\n#energy to power 1 homes for a year\nEnergyPerYear = 100e6 #J\nprint(f'Energy could power {(CombustionEnergy+BurstEnergy)/EnergyPerYear:.2f} homes for a year')","key":"hcNgvbCnkf"},{"type":"output","id":"CuPWpnaL_1C0uksKeDS5v","data":[{"name":"stdout","output_type":"stream","text":"BurstEnergy, MJ:  121.29319730813798\nCombustionEnergy, MJ: 399183.10\nEnergy could power 3993.04 homes for a year\n"}],"key":"EJWylAEj1P"}],"key":"IdRp9bPOLT"},{"type":"block","kind":"notebook-content","children":[{"type":"paragraph","position":{"start":{"line":1,"column":1},"end":{"line":1,"column":1}},"children":[{"type":"text","value":"What steps could be taken to prevent the reactor from over-pressurizing?","position":{"start":{"line":1,"column":1},"end":{"line":1,"column":1}},"key":"nPB4dRJbQT"}],"key":"gQc27X61vH"}],"key":"rwjsV6V458"},{"type":"block","kind":"notebook-content","children":[{"type":"admonition","kind":"note","children":[{"type":"admonitionTitle","children":[{"type":"text","value":"Note","key":"TCJB4NKrZ7"}],"key":"dxIrAkZCK1"},{"type":"list","ordered":false,"spread":false,"position":{"start":{"line":2,"column":1},"end":{"line":6,"column":1}},"children":[{"type":"listItem","spread":true,"position":{"start":{"line":2,"column":1},"end":{"line":2,"column":1}},"children":[{"type":"text","value":"Effective control of the rate of the reaction(s)","position":{"start":{"line":2,"column":1},"end":{"line":2,"column":1}},"key":"ESkhQ9UzSM"}],"key":"EvKOrgiwS5"},{"type":"listItem","spread":true,"position":{"start":{"line":3,"column":1},"end":{"line":3,"column":1}},"children":[{"type":"text","value":"Specific strategies to control side reactions","position":{"start":{"line":3,"column":1},"end":{"line":3,"column":1}},"key":"VLBmeWPRTm"}],"key":"rxXF57Gex2"},{"type":"listItem","spread":true,"position":{"start":{"line":4,"column":1},"end":{"line":4,"column":1}},"children":[{"type":"text","value":"Effective reactor cooling","position":{"start":{"line":4,"column":1},"end":{"line":4,"column":1}},"key":"dZ7VfmvKbx"}],"key":"uoqdkspu52"},{"type":"listItem","spread":true,"position":{"start":{"line":5,"column":1},"end":{"line":5,"column":1}},"children":[{"type":"strong","position":{"start":{"line":5,"column":1},"end":{"line":5,"column":1}},"children":[{"type":"text","value":"Pressure Relief Devices","position":{"start":{"line":5,"column":1},"end":{"line":5,"column":1}},"key":"zciAhKN0ma"}],"key":"EDI6UinC2T"},{"type":"text","value":" can be used to prevent an over-pressurization scenario","position":{"start":{"line":5,"column":1},"end":{"line":5,"column":1}},"key":"vzcDpUYGV4"}],"key":"lPN1wRCWL0"},{"type":"listItem","spread":true,"position":{"start":{"line":6,"column":1},"end":{"line":6,"column":1}},"children":[{"type":"text","value":"RAGAGEP (Recognized and Generally Accepted Good Engineering Practices) should be followed","position":{"start":{"line":6,"column":1},"end":{"line":6,"column":1}},"key":"efvCKed8OT"}],"key":"IoTcmwH8de"}],"key":"PKxUXn9PMb"}],"key":"c6uZEStrld"}],"key":"B8YRN4dnpf"},{"type":"block","kind":"notebook-content","children":[{"type":"paragraph","position":{"start":{"line":1,"column":1},"end":{"line":1,"column":1}},"children":[{"type":"text","value":"Code requirements (RAGAGEP) for pressure relief devices are found in Boiler and Pressure Vessel Code (ASME), Section VIII, Division 1, API 520, and others.","position":{"start":{"line":1,"column":1},"end":{"line":1,"column":1}},"key":"F6VNIY96HE"}],"key":"jDekI2GZz1"},{"type":"paragraph","position":{"start":{"line":3,"column":1},"end":{"line":3,"column":1}},"children":[{"type":"text","value":"Many vessels are required to have pressure relief protection including","position":{"start":{"line":3,"column":1},"end":{"line":3,"column":1}},"key":"fMvUScwRUh"}],"key":"NXvshgq4gN"},{"type":"list","ordered":false,"spread":false,"position":{"start":{"line":5,"column":1},"end":{"line":8,"column":1}},"children":[{"type":"listItem","spread":true,"position":{"start":{"line":5,"column":1},"end":{"line":5,"column":1}},"children":[{"type":"text","value":"Pressure vessels","position":{"start":{"line":5,"column":1},"end":{"line":5,"column":1}},"key":"GrGT5rDtcM"}],"key":"MyfJanOHBJ"},{"type":"listItem","spread":true,"position":{"start":{"line":6,"column":1},"end":{"line":6,"column":1}},"children":[{"type":"text","value":"Blocked-in sections of liquid-filled piping","position":{"start":{"line":6,"column":1},"end":{"line":6,"column":1}},"key":"ocx7btZZl3"}],"key":"P3GY91WiuJ"},{"type":"listItem","spread":true,"position":{"start":{"line":7,"column":1},"end":{"line":7,"column":1}},"children":[{"type":"text","value":"Heat exchangers","position":{"start":{"line":7,"column":1},"end":{"line":7,"column":1}},"key":"CW37UVmBbX"}],"key":"b16HG7RIiI"},{"type":"listItem","spread":true,"position":{"start":{"line":8,"column":1},"end":{"line":8,"column":1}},"children":[{"type":"text","value":"Storage tanks","position":{"start":{"line":8,"column":1},"end":{"line":8,"column":1}},"key":"CqD8IIyS6t"}],"key":"XNQCL6CJwa"}],"key":"wP008ob0Nc"}],"key":"g1NS7Jbd7K"},{"type":"block","kind":"notebook-content","children":[{"type":"paragraph","position":{"start":{"line":1,"column":1},"end":{"line":1,"column":1}},"children":[{"type":"text","value":"What are some ways that elevated pressures could occur?","position":{"start":{"line":1,"column":1},"end":{"line":1,"column":1}},"key":"IUkPF6ronS"}],"key":"wxjFiHdx6D"},{"type":"admonition","kind":"note","children":[{"type":"admonitionTitle","children":[{"type":"text","value":"Note","key":"vlJEa0Lvdv"}],"key":"LOOKS5ZXPL"},{"type":"list","ordered":false,"spread":false,"position":{"start":{"line":4,"column":1},"end":{"line":14,"column":1}},"children":[{"type":"listItem","spread":true,"position":{"start":{"line":4,"column":1},"end":{"line":4,"column":1}},"children":[{"type":"text","value":"Overheating","position":{"start":{"line":4,"column":1},"end":{"line":4,"column":1}},"key":"IG6kvrKgWn"}],"key":"HOXzJE9yvZ"},{"type":"listItem","spread":true,"position":{"start":{"line":5,"column":1},"end":{"line":5,"column":1}},"children":[{"type":"text","value":"Runaway reaction","position":{"start":{"line":5,"column":1},"end":{"line":5,"column":1}},"key":"OUkM4xrJPz"}],"key":"mVY5b3xRpI"},{"type":"listItem","spread":true,"position":{"start":{"line":6,"column":1},"end":{"line":6,"column":1}},"children":[{"type":"text","value":"Blocked outlet","position":{"start":{"line":6,"column":1},"end":{"line":6,"column":1}},"key":"dlQwhF4G2r"}],"key":"SMUkc3XVaa"},{"type":"listItem","spread":true,"position":{"start":{"line":7,"column":1},"end":{"line":7,"column":1}},"children":[{"type":"text","value":"Fire exposure","position":{"start":{"line":7,"column":1},"end":{"line":7,"column":1}},"key":"uiyRV9srUD"}],"key":"XNqaF3LBcw"},{"type":"listItem","spread":true,"position":{"start":{"line":8,"column":1},"end":{"line":8,"column":1}},"children":[{"type":"text","value":"External pressure","position":{"start":{"line":8,"column":1},"end":{"line":8,"column":1}},"key":"c5EAK4qhTH"}],"key":"FCynOGC4D7"},{"type":"listItem","spread":true,"position":{"start":{"line":9,"column":1},"end":{"line":9,"column":1}},"children":[{"type":"text","value":"Thermal expansion","position":{"start":{"line":9,"column":1},"end":{"line":9,"column":1}},"key":"YwAEru67e0"}],"key":"Ebqsfu4sFk"},{"type":"listItem","spread":true,"position":{"start":{"line":10,"column":1},"end":{"line":10,"column":1}},"children":[{"type":"text","value":"Overfilling","position":{"start":{"line":10,"column":1},"end":{"line":10,"column":1}},"key":"UC44TOfiaC"}],"key":"WSnwDEXDE3"},{"type":"listItem","spread":true,"position":{"start":{"line":11,"column":1},"end":{"line":11,"column":1}},"children":[{"type":"text","value":"Equipment failure","position":{"start":{"line":11,"column":1},"end":{"line":11,"column":1}},"key":"JEgMuaoH8z"}],"key":"NJ9rR6WT4F"},{"type":"listItem","spread":true,"position":{"start":{"line":12,"column":1},"end":{"line":12,"column":1}},"children":[{"type":"text","value":"Control system failure","position":{"start":{"line":12,"column":1},"end":{"line":12,"column":1}},"key":"ItmWFekZiy"}],"key":"ZQjEW360oE"},{"type":"listItem","spread":true,"position":{"start":{"line":13,"column":1},"end":{"line":13,"column":1}},"children":[{"type":"text","value":"Operator error","position":{"start":{"line":13,"column":1},"end":{"line":13,"column":1}},"key":"dxIquL2aIl"}],"key":"Uv0t8ksyhz"},{"type":"listItem","spread":true,"position":{"start":{"line":14,"column":1},"end":{"line":14,"column":1}},"children":[{"type":"text","value":"Instrumentation failure","position":{"start":{"line":14,"column":1},"end":{"line":14,"column":1}},"key":"scJ7CqZiXw"}],"key":"vAIaCdyIzT"}],"key":"H34RfuJOK7"}],"key":"A7c8Oun5qw"}],"key":"QqH9CMsosN"},{"type":"block","kind":"notebook-content","children":[{"type":"heading","depth":2,"position":{"start":{"line":1,"column":1},"end":{"line":1,"column":1}},"children":[{"type":"text","value":"Types of Pressure Protection Devices","position":{"start":{"line":1,"column":1},"end":{"line":1,"column":1}},"key":"ppUglP7W04"}],"identifier":"types-of-pressure-protection-devices","label":"Types of Pressure Protection Devices","html_id":"types-of-pressure-protection-devices","implicit":true,"key":"f7pWMC09yG"}],"key":"Fojv7P3nal"},{"type":"block","kind":"notebook-content","children":[{"type":"heading","depth":3,"position":{"start":{"line":1,"column":1},"end":{"line":1,"column":1}},"children":[{"type":"text","value":"Spring Operated Relief Valves","position":{"start":{"line":1,"column":1},"end":{"line":1,"column":1}},"key":"nmQlmSPMZY"}],"identifier":"spring-operated-relief-valves","label":"Spring Operated Relief Valves","html_id":"spring-operated-relief-valves","implicit":true,"key":"YAPeufzozE"}],"key":"CKToc2jPcc"},{"type":"block","kind":"notebook-content","children":[{"type":"paragraph","position":{"start":{"line":1,"column":1},"end":{"line":1,"column":1}},"children":[{"type":"image","url":"/9204074c9ac0a1334dbd2ff7a0b2a88a.png","width":300,"key":"tQNJPJg6xW","urlSource":"https://github.com/clint-bg/safetyinjc/blob/main/physical/supportfiles/springrelief.png?raw=true","urlOptimized":"/9204074c9ac0a1334dbd2ff7a0b2a88a.webp"},{"type":"image","url":"/ff2968e8a2366841ad34ab43daf94d36.png","width":300,"key":"BmB6W28d0p","urlSource":"https://github.com/clint-bg/safetyinjc/blob/main/physical/supportfiles/springrelief2.png?raw=true","urlOptimized":"/ff2968e8a2366841ad34ab43daf94d36.webp"}],"key":"O1AFAQBCUk"}],"key":"nL2CVOFfji"},{"type":"block","kind":"notebook-content","children":[{"type":"paragraph","position":{"start":{"line":1,"column":1},"end":{"line":1,"column":1}},"children":[{"type":"text","value":"Some components of spring operated relief valves include:","position":{"start":{"line":1,"column":1},"end":{"line":1,"column":1}},"key":"LAyw6fusiK"}],"key":"jR1MT64f5I"},{"type":"list","ordered":false,"spread":false,"position":{"start":{"line":3,"column":1},"end":{"line":6,"column":1}},"children":[{"type":"listItem","spread":true,"position":{"start":{"line":3,"column":1},"end":{"line":3,"column":1}},"children":[{"type":"text","value":"Spring - the spring is compressed by the process pressure","position":{"start":{"line":3,"column":1},"end":{"line":3,"column":1}},"key":"TFfynOIMYH"}],"key":"EF9J7epE7C"},{"type":"listItem","spread":true,"position":{"start":{"line":4,"column":1},"end":{"line":4,"column":1}},"children":[{"type":"text","value":"Valve plug - the plug is lifted off the seat when the spring force is overcome by the process pressure","position":{"start":{"line":4,"column":1},"end":{"line":4,"column":1}},"key":"hKeaRk4GKH"}],"key":"WNu7v9WsVy"},{"type":"listItem","spread":true,"position":{"start":{"line":5,"column":1},"end":{"line":5,"column":1}},"children":[{"type":"text","value":"Nozzle - the nozzle directs the flow of the relieving fluid","position":{"start":{"line":5,"column":1},"end":{"line":5,"column":1}},"key":"vVoBeQPxGn"}],"key":"I9hKMrvLxW"},{"type":"listItem","spread":true,"position":{"start":{"line":6,"column":1},"end":{"line":6,"column":1}},"children":[{"type":"text","value":"Seat - the plug seals against the seat to prevent flow","position":{"start":{"line":6,"column":1},"end":{"line":6,"column":1}},"key":"EV1yXg61kf"}],"key":"mC2wX37xqa"}],"key":"ooZVms19Iv"}],"key":"bUdZNVNxka"},{"type":"block","kind":"notebook-content","children":[{"type":"paragraph","position":{"start":{"line":1,"column":1},"end":{"line":1,"column":1}},"children":[{"type":"text","value":"Comments on spring operated relief valves:","position":{"start":{"line":1,"column":1},"end":{"line":1,"column":1}},"key":"p4jxp6nkrb"}],"key":"pqrILnM3u6"},{"type":"list","ordered":false,"spread":false,"position":{"start":{"line":3,"column":1},"end":{"line":8,"column":1}},"children":[{"type":"listItem","spread":true,"position":{"start":{"line":3,"column":1},"end":{"line":3,"column":1}},"children":[{"type":"text","value":"very common","position":{"start":{"line":3,"column":1},"end":{"line":3,"column":1}},"key":"rLHcUldEK9"}],"key":"zzl3SR1Mwt"},{"type":"listItem","spread":true,"position":{"start":{"line":4,"column":1},"end":{"line":4,"column":1}},"children":[{"type":"text","value":"versatile: can be used for gas or liquid","position":{"start":{"line":4,"column":1},"end":{"line":4,"column":1}},"key":"O3Cilrl2qz"}],"key":"In1wuu6t3q"},{"type":"listItem","spread":true,"position":{"start":{"line":5,"column":1},"end":{"line":5,"column":1}},"children":[{"type":"text","value":"reliable","position":{"start":{"line":5,"column":1},"end":{"line":5,"column":1}},"key":"QnwAjUjd2S"}],"key":"tcY3RN6BZc"},{"type":"listItem","spread":true,"position":{"start":{"line":6,"column":1},"end":{"line":6,"column":1}},"children":[{"type":"text","value":"susceptible to chatter","position":{"start":{"line":6,"column":1},"end":{"line":6,"column":1}},"key":"L8qyHmTKmi"}],"key":"uTMA6GY4Ws"},{"type":"listItem","spread":true,"position":{"start":{"line":7,"column":1},"end":{"line":7,"column":1}},"children":[{"type":"text","value":"relieving pressure affected by temperature, back pressure, and accumulation","position":{"start":{"line":7,"column":1},"end":{"line":7,"column":1}},"key":"nYLmh08lTJ"}],"key":"aCr61NpXMM"},{"type":"listItem","spread":true,"position":{"start":{"line":8,"column":1},"end":{"line":8,"column":1}},"children":[{"type":"text","value":"flow decreases with increasing back pressure","position":{"start":{"line":8,"column":1},"end":{"line":8,"column":1}},"key":"i5ZEYd58p1"}],"key":"tuyrFzTa5h"}],"key":"qhqvDywTJs"}],"key":"Pc8bd7EgoU"},{"type":"block","kind":"notebook-content","children":[{"type":"heading","depth":3,"position":{"start":{"line":1,"column":1},"end":{"line":1,"column":1}},"children":[{"type":"text","value":"Balanced Bellows Relief Valves","position":{"start":{"line":1,"column":1},"end":{"line":1,"column":1}},"key":"oVIo3LJck2"}],"identifier":"balanced-bellows-relief-valves","label":"Balanced Bellows Relief Valves","html_id":"balanced-bellows-relief-valves","implicit":true,"key":"wxNCDUe95C"}],"key":"EWaf9vrcoa"},{"type":"block","kind":"notebook-content","children":[{"type":"paragraph","position":{"start":{"line":1,"column":1},"end":{"line":1,"column":1}},"children":[{"type":"image","url":"/7b7ac322ddc84193d37e350bce95f57a.png","width":300,"key":"WZCzBSkf9F","urlSource":"https://github.com/clint-bg/safetyinjc/blob/main/physical/supportfiles/bellowsrelief.png?raw=true","urlOptimized":"/7b7ac322ddc84193d37e350bce95f57a.webp"},{"type":"image","url":"/66866f0a50d5368208b71ae63d42c8fb.png","width":300,"key":"PkdFwODv0s","urlSource":"https://github.com/clint-bg/safetyinjc/blob/main/physical/supportfiles/bellowsrelief2.png?raw=true","urlOptimized":"/66866f0a50d5368208b71ae63d42c8fb.webp"}],"key":"U2oZCxx7jx"}],"key":"l677DkSGlA"},{"type":"block","kind":"notebook-content","children":[{"type":"paragraph","position":{"start":{"line":1,"column":1},"end":{"line":1,"column":1}},"children":[{"type":"text","value":"Some components of balanced bellows relief valves include:","position":{"start":{"line":1,"column":1},"end":{"line":1,"column":1}},"key":"i216BbIFX0"}],"key":"FORgY3hEEb"},{"type":"list","ordered":false,"spread":false,"position":{"start":{"line":3,"column":1},"end":{"line":6,"column":1}},"children":[{"type":"listItem","spread":true,"position":{"start":{"line":3,"column":1},"end":{"line":3,"column":1}},"children":[{"type":"text","value":"Bellows - the bellows is a flexible diaphragm that is used to sense the process pressure","position":{"start":{"line":3,"column":1},"end":{"line":3,"column":1}},"key":"rBRG7dmhKF"}],"key":"Dn3hQpQRgT"},{"type":"listItem","spread":true,"position":{"start":{"line":4,"column":1},"end":{"line":4,"column":1}},"children":[{"type":"text","value":"Valve plug - the plug is lifted off the seat when the bellows force is overcome by the process pressure","position":{"start":{"line":4,"column":1},"end":{"line":4,"column":1}},"key":"JDMwgbKiH9"}],"key":"YehoNsf5O4"},{"type":"listItem","spread":true,"position":{"start":{"line":5,"column":1},"end":{"line":5,"column":1}},"children":[{"type":"text","value":"Nozzle - the nozzle directs the flow of the relieving fluid","position":{"start":{"line":5,"column":1},"end":{"line":5,"column":1}},"key":"zsp2YOaOsN"}],"key":"mjJ8j2O5uw"},{"type":"listItem","spread":true,"position":{"start":{"line":6,"column":1},"end":{"line":6,"column":1}},"children":[{"type":"text","value":"Seat - the plug seals against the seat to prevent flow","position":{"start":{"line":6,"column":1},"end":{"line":6,"column":1}},"key":"yf6Dws7K1N"}],"key":"xGIYO2k3V6"}],"key":"veQXZfsrIW"}],"key":"PlzM9zFtV1"},{"type":"block","kind":"notebook-content","children":[{"type":"paragraph","position":{"start":{"line":1,"column":1},"end":{"line":1,"column":1}},"children":[{"type":"text","value":"Comments on balanced bellows relief valves:","position":{"start":{"line":1,"column":1},"end":{"line":1,"column":1}},"key":"bZJTj7f852"}],"key":"pwRdyrMPCm"},{"type":"list","ordered":false,"spread":false,"position":{"start":{"line":3,"column":1},"end":{"line":7,"column":1}},"children":[{"type":"listItem","spread":true,"position":{"start":{"line":3,"column":1},"end":{"line":3,"column":1}},"children":[{"type":"text","value":"similar to spring operated relief valves","position":{"start":{"line":3,"column":1},"end":{"line":3,"column":1}},"key":"MRIFKia0Ib"}],"key":"VSDbf1bxMG"},{"type":"listItem","spread":true,"position":{"start":{"line":4,"column":1},"end":{"line":4,"column":1}},"children":[{"type":"text","value":"relieving pressure is not affected by back pressure","position":{"start":{"line":4,"column":1},"end":{"line":4,"column":1}},"key":"VrVEgavZzg"}],"key":"ITkSMA6dYH"},{"type":"listItem","spread":true,"position":{"start":{"line":5,"column":1},"end":{"line":5,"column":1}},"children":[{"type":"text","value":"flow decreases with increasing back pressure","position":{"start":{"line":5,"column":1},"end":{"line":5,"column":1}},"key":"FUqJ1nLx0Q"}],"key":"y2N3Fy4Don"},{"type":"listItem","spread":true,"position":{"start":{"line":6,"column":1},"end":{"line":6,"column":1}},"children":[{"type":"text","value":"spring is protected from the process fluid","position":{"start":{"line":6,"column":1},"end":{"line":6,"column":1}},"key":"b2p5xfCHqB"}],"key":"zm33v6eRe8"},{"type":"listItem","spread":true,"position":{"start":{"line":7,"column":1},"end":{"line":7,"column":1}},"children":[{"type":"text","value":"flow through the valve can be impacted by back pressure","position":{"start":{"line":7,"column":1},"end":{"line":7,"column":1}},"key":"uzyy65gAAI"}],"key":"jBOFIVF2mW"}],"key":"aYHNChRhlm"}],"key":"xvdM55Dxoo"},{"type":"block","kind":"notebook-content","children":[{"type":"heading","depth":3,"position":{"start":{"line":1,"column":1},"end":{"line":1,"column":1}},"children":[{"type":"text","value":"Pilot Operated Relief Valves","position":{"start":{"line":1,"column":1},"end":{"line":1,"column":1}},"key":"cS8WClexgf"}],"identifier":"pilot-operated-relief-valves","label":"Pilot Operated Relief Valves","html_id":"pilot-operated-relief-valves","implicit":true,"key":"VBd9tfgbNa"}],"key":"HTiAsaC4nz"},{"type":"block","kind":"notebook-content","children":[{"type":"paragraph","position":{"start":{"line":1,"column":1},"end":{"line":1,"column":1}},"children":[{"type":"text","value":"Some comments on pilot operated relief valves:","position":{"start":{"line":1,"column":1},"end":{"line":1,"column":1}},"key":"gD8sWpG2K9"}],"key":"QsETMYE5EM"},{"type":"list","ordered":false,"spread":false,"position":{"start":{"line":2,"column":1},"end":{"line":5,"column":1}},"children":[{"type":"listItem","spread":true,"position":{"start":{"line":2,"column":1},"end":{"line":2,"column":1}},"children":[{"type":"text","value":"relieving pressure not affected by back pressure","position":{"start":{"line":2,"column":1},"end":{"line":2,"column":1}},"key":"cG2YWorKAg"}],"key":"k0AytLwqas"},{"type":"listItem","spread":true,"position":{"start":{"line":3,"column":1},"end":{"line":3,"column":1}},"children":[{"type":"text","value":"can operate very close to set pressure","position":{"start":{"line":3,"column":1},"end":{"line":3,"column":1}},"key":"WCm1LFKd08"}],"key":"CVcuA6wF2s"},{"type":"listItem","spread":true,"position":{"start":{"line":4,"column":1},"end":{"line":4,"column":1}},"children":[{"type":"text","value":"potential for back flow","position":{"start":{"line":4,"column":1},"end":{"line":4,"column":1}},"key":"c7gdU9COfM"}],"key":"N8LLpSTJ35"},{"type":"listItem","spread":true,"position":{"start":{"line":5,"column":1},"end":{"line":5,"column":1}},"children":[{"type":"text","value":"o-ring seals limit some applications","position":{"start":{"line":5,"column":1},"end":{"line":5,"column":1}},"key":"Jp4vCgZEDF"}],"key":"PqWAyY6YrA"}],"key":"kicfHEFk1c"}],"key":"TGCvPgdNCP"},{"type":"block","kind":"notebook-content","children":[{"type":"heading","depth":3,"position":{"start":{"line":1,"column":1},"end":{"line":1,"column":1}},"children":[{"type":"text","value":"Buckling Pin Relief Valves","position":{"start":{"line":1,"column":1},"end":{"line":1,"column":1}},"key":"sHfVVWTcsW"}],"identifier":"buckling-pin-relief-valves","label":"Buckling Pin Relief Valves","html_id":"buckling-pin-relief-valves","implicit":true,"key":"FN1qrvWiMy"}],"key":"QPbUwdyGVY"},{"type":"block","kind":"notebook-content","children":[{"type":"paragraph","position":{"start":{"line":1,"column":1},"end":{"line":1,"column":1}},"children":[{"type":"text","value":"Comments on buckling pin relief valves:","position":{"start":{"line":1,"column":1},"end":{"line":1,"column":1}},"key":"BbU9w7PQBu"}],"key":"uwazD0Li1T"},{"type":"list","ordered":false,"spread":false,"position":{"start":{"line":2,"column":1},"end":{"line":6,"column":1}},"children":[{"type":"listItem","spread":true,"position":{"start":{"line":2,"column":1},"end":{"line":2,"column":1}},"children":[{"type":"text","value":"similar to a rupture disk","position":{"start":{"line":2,"column":1},"end":{"line":2,"column":1}},"key":"EQOdCE8lCZ"}],"key":"rkL6aF1HVz"},{"type":"listItem","spread":true,"position":{"start":{"line":3,"column":1},"end":{"line":3,"column":1}},"children":[{"type":"text","value":"o-ring seals used and can limit some applications","position":{"start":{"line":3,"column":1},"end":{"line":3,"column":1}},"key":"vh7JEXSrwS"}],"key":"r8x5KwYYcV"},{"type":"listItem","spread":true,"position":{"start":{"line":4,"column":1},"end":{"line":4,"column":1}},"children":[{"type":"text","value":"less susceptible to corrosion (vs rupture disk)","position":{"start":{"line":4,"column":1},"end":{"line":4,"column":1}},"key":"SXIJLhemUL"}],"key":"IZjZ5yvvVg"},{"type":"listItem","spread":true,"position":{"start":{"line":5,"column":1},"end":{"line":5,"column":1}},"children":[{"type":"text","value":"can be operated closer to the set pressure (vs rupture disk)","position":{"start":{"line":5,"column":1},"end":{"line":5,"column":1}},"key":"o8XNRYxp8m"}],"key":"sDONE7Yx6B"},{"type":"listItem","spread":true,"position":{"start":{"line":6,"column":1},"end":{"line":6,"column":1}},"children":[{"type":"text","value":"can operate at very low set pressures","position":{"start":{"line":6,"column":1},"end":{"line":6,"column":1}},"key":"wxNQQ4w5dv"}],"key":"pGQWYgB7BC"}],"key":"sjIK4K9ILr"}],"key":"hXUj19fixk"},{"type":"block","kind":"notebook-content","children":[{"type":"heading","depth":3,"position":{"start":{"line":1,"column":1},"end":{"line":1,"column":1}},"children":[{"type":"text","value":"Rupture Disks","position":{"start":{"line":1,"column":1},"end":{"line":1,"column":1}},"key":"LoYSpYFdXK"}],"identifier":"rupture-disks","label":"Rupture Disks","html_id":"rupture-disks","implicit":true,"key":"YD3tgfCb2g"}],"key":"S2TQoYN6RP"},{"type":"block","kind":"notebook-content","children":[{"type":"paragraph","position":{"start":{"line":1,"column":1},"end":{"line":1,"column":1}},"children":[{"type":"image","url":"/d4897f179d4e3d4b2c3e2325cbb7f32e.png","width":300,"key":"z2xU5ADh6j","urlSource":"https://github.com/clint-bg/safetyinjc/blob/main/physical/supportfiles/rupturerelief.png?raw=true","urlOptimized":"/d4897f179d4e3d4b2c3e2325cbb7f32e.webp"},{"type":"image","url":"/d7527246d9ee124053ada36c25bb4a27.png","width":300,"key":"xQSss0vwY3","urlSource":"https://github.com/clint-bg/safetyinjc/blob/main/physical/supportfiles/rupturerelief2.png?raw=true","urlOptimized":"/d7527246d9ee124053ada36c25bb4a27.webp"}],"key":"VJFsI8YCG4"}],"key":"n4SQaSPhUF"},{"type":"block","kind":"notebook-content","children":[{"type":"paragraph","position":{"start":{"line":1,"column":1},"end":{"line":1,"column":1}},"children":[{"type":"text","value":"Relief valves are often used in conjunction with rupture disks. Rupture disks are used to protect the relief valve from the process fluid. Rupture disks are often used in applications where the process fluid is corrosive, toxic, or would otherwise damage the relief valve.","position":{"start":{"line":1,"column":1},"end":{"line":1,"column":1}},"key":"OPhJs8xcB0"}],"key":"gBBTUznbUu"}],"key":"MgkkSMU6dx"},{"type":"block","kind":"notebook-content","children":[{"type":"paragraph","position":{"start":{"line":1,"column":1},"end":{"line":1,"column":1}},"children":[{"type":"text","value":"Rupture disks are often made of a thin metal that is designed to rupture at a specific pressure. The rupture disk is installed in a holder that is designed to contain the disk fragments when the disk ruptures. Some other characteristics of rupture disks include:","position":{"start":{"line":1,"column":1},"end":{"line":1,"column":1}},"key":"gA0lBoxoup"}],"key":"MU0gebc3bf"},{"type":"list","ordered":false,"spread":false,"position":{"start":{"line":3,"column":1},"end":{"line":16,"column":1}},"children":[{"type":"listItem","spread":true,"position":{"start":{"line":3,"column":1},"end":{"line":3,"column":1}},"children":[{"type":"text","value":"often used in conjunction with relief valves","position":{"start":{"line":3,"column":1},"end":{"line":3,"column":1}},"key":"cwZX81CgZ6"}],"key":"V2VmPVvQXW"},{"type":"listItem","spread":true,"position":{"start":{"line":4,"column":1},"end":{"line":4,"column":1}},"children":[{"type":"text","value":"often used in applications where the process fluid is corrosive, toxic, or would otherwise damage the relief valve or small leaks over time would present risks to people and the environment","position":{"start":{"line":4,"column":1},"end":{"line":4,"column":1}},"key":"sXttAFUMNI"}],"key":"Ccg6DqpOwf"},{"type":"listItem","spread":true,"position":{"start":{"line":5,"column":1},"end":{"line":5,"column":1}},"children":[{"type":"text","value":"one-time use (does not close after relieving)","position":{"start":{"line":5,"column":1},"end":{"line":5,"column":1}},"key":"d4NqJt6VBf"}],"key":"BTUSYaM5my"},{"type":"listItem","spread":true,"position":{"start":{"line":6,"column":1},"end":{"line":6,"column":1}},"children":[{"type":"text","value":"pieces of disk can be a hazard in the process","position":{"start":{"line":6,"column":1},"end":{"line":6,"column":1}},"key":"lcmkwbIGHy"}],"key":"wlPrOV3xUX"},{"type":"listItem","spread":true,"position":{"start":{"line":7,"column":1},"end":{"line":7,"column":1}},"children":[{"type":"text","value":"rapid response","position":{"start":{"line":7,"column":1},"end":{"line":7,"column":1}},"key":"ffmr6AsvQR"}],"key":"owMzUndHbo"},{"type":"listItem","spread":true,"position":{"start":{"line":8,"column":1},"end":{"line":16,"column":1}},"children":[{"type":"text","value":"there are multiple types:","position":{"start":{"line":8,"column":1},"end":{"line":8,"column":1}},"key":"xg09ytFZLk"},{"type":"list","ordered":false,"spread":false,"position":{"start":{"line":9,"column":1},"end":{"line":16,"column":1}},"children":[{"type":"listItem","spread":true,"position":{"start":{"line":9,"column":1},"end":{"line":9,"column":1}},"children":[{"type":"text","value":"reverse buckling","position":{"start":{"line":9,"column":1},"end":{"line":9,"column":1}},"key":"FId0Mz5AIB"}],"key":"rFOIYf3UX9"},{"type":"listItem","spread":true,"position":{"start":{"line":10,"column":1},"end":{"line":10,"column":1}},"children":[{"type":"text","value":"tension loaded","position":{"start":{"line":10,"column":1},"end":{"line":10,"column":1}},"key":"BmGXiW1FSf"}],"key":"YX4vPSXRkQ"},{"type":"listItem","spread":true,"position":{"start":{"line":11,"column":1},"end":{"line":11,"column":1}},"children":[{"type":"text","value":"scored","position":{"start":{"line":11,"column":1},"end":{"line":11,"column":1}},"key":"hnE2A5Emoa"}],"key":"gqOcVVugVm"},{"type":"listItem","spread":true,"position":{"start":{"line":12,"column":1},"end":{"line":12,"column":1}},"children":[{"type":"text","value":"pre-fragmented","position":{"start":{"line":12,"column":1},"end":{"line":12,"column":1}},"key":"fOw6q40Aoi"}],"key":"Pavrs6q98r"},{"type":"listItem","spread":true,"position":{"start":{"line":13,"column":1},"end":{"line":13,"column":1}},"children":[{"type":"text","value":"composite","position":{"start":{"line":13,"column":1},"end":{"line":13,"column":1}},"key":"FcgiOUkLn8"}],"key":"gOoKO0HjB1"},{"type":"listItem","spread":true,"position":{"start":{"line":14,"column":1},"end":{"line":14,"column":1}},"children":[{"type":"text","value":"solid","position":{"start":{"line":14,"column":1},"end":{"line":14,"column":1}},"key":"NrF8xhYyHg"}],"key":"f1DFZSf4kU"},{"type":"listItem","spread":true,"position":{"start":{"line":15,"column":1},"end":{"line":15,"column":1}},"children":[{"type":"text","value":"knife blade","position":{"start":{"line":15,"column":1},"end":{"line":15,"column":1}},"key":"HfI3WfsDlF"}],"key":"lOZX7A3BM9"},{"type":"listItem","spread":true,"position":{"start":{"line":16,"column":1},"end":{"line":16,"column":1}},"children":[{"type":"text","value":"slotted","position":{"start":{"line":16,"column":1},"end":{"line":16,"column":1}},"key":"LaR7pJ08ER"}],"key":"vMF0730iRa"}],"key":"u00ddQ5vW1"}],"key":"GBUpwB1bQF"}],"key":"v8YJq4purD"}],"key":"AFCbbJrgXJ"},{"type":"block","kind":"notebook-content","children":[{"type":"heading","depth":2,"position":{"start":{"line":1,"column":1},"end":{"line":1,"column":1}},"children":[{"type":"text","value":"Some Definitions","position":{"start":{"line":1,"column":1},"end":{"line":1,"column":1}},"key":"gXOlLJmZa7"}],"identifier":"some-definitions","label":"Some Definitions","html_id":"some-definitions","implicit":true,"key":"idswV6pY24"},{"type":"table","position":{"start":{"line":3,"column":1},"end":{"line":16,"column":1}},"children":[{"type":"tableRow","position":{"start":{"line":3,"column":1},"end":{"line":3,"column":1}},"children":[{"type":"tableCell","header":true,"position":{"start":{"line":3,"column":1},"end":{"line":3,"column":1}},"children":[{"type":"text","value":"Term","position":{"start":{"line":3,"column":1},"end":{"line":3,"column":1}},"key":"WOMBfcIwSp"}],"key":"SEIQkA1RZX"},{"type":"tableCell","header":true,"position":{"start":{"line":3,"column":1},"end":{"line":3,"column":1}},"children":[{"type":"text","value":"Definition","position":{"start":{"line":3,"column":1},"end":{"line":3,"column":1}},"key":"FuViBACIzi"}],"key":"UyJtG0IbfB"}],"key":"xDwbxdmsAk"},{"type":"tableRow","position":{"start":{"line":5,"column":1},"end":{"line":5,"column":1}},"children":[{"type":"tableCell","position":{"start":{"line":5,"column":1},"end":{"line":5,"column":1}},"children":[{"type":"text","value":"Set Pressure","position":{"start":{"line":5,"column":1},"end":{"line":5,"column":1}},"key":"b79k5IZE3T"}],"key":"p3202WuOKI"},{"type":"tableCell","position":{"start":{"line":5,"column":1},"end":{"line":5,"column":1}},"children":[{"type":"text","value":"The pressure at which the relief device is set to open","position":{"start":{"line":5,"column":1},"end":{"line":5,"column":1}},"key":"EBh8WuMJAz"}],"key":"KPGK2dBezb"}],"key":"c4NecGI7Ww"},{"type":"tableRow","position":{"start":{"line":6,"column":1},"end":{"line":6,"column":1}},"children":[{"type":"tableCell","position":{"start":{"line":6,"column":1},"end":{"line":6,"column":1}},"children":[{"type":"text","value":"Relief Pressure","position":{"start":{"line":6,"column":1},"end":{"line":6,"column":1}},"key":"TLuW5fYxKK"}],"key":"fhzJSihf3r"},{"type":"tableCell","position":{"start":{"line":6,"column":1},"end":{"line":6,"column":1}},"children":[{"type":"text","value":"The pressure at which the relief device actually opens","position":{"start":{"line":6,"column":1},"end":{"line":6,"column":1}},"key":"NcTRJU5urn"}],"key":"UmW6bHJXTi"}],"key":"gpEvqwNgIh"},{"type":"tableRow","position":{"start":{"line":7,"column":1},"end":{"line":7,"column":1}},"children":[{"type":"tableCell","position":{"start":{"line":7,"column":1},"end":{"line":7,"column":1}},"children":[{"type":"text","value":"MAWP","position":{"start":{"line":7,"column":1},"end":{"line":7,"column":1}},"key":"RUrQXOD7cy"}],"key":"Oj9TH1m9Ps"},{"type":"tableCell","position":{"start":{"line":7,"column":1},"end":{"line":7,"column":1}},"children":[{"type":"text","value":"Maximum Allowable Working Pressure, maximum gauge pressure permissible at the top of the vessel at the designated temperature","position":{"start":{"line":7,"column":1},"end":{"line":7,"column":1}},"key":"TfJTU4vfaj"}],"key":"jkOjVQshg4"}],"key":"mFzimIzAvX"},{"type":"tableRow","position":{"start":{"line":8,"column":1},"end":{"line":8,"column":1}},"children":[{"type":"tableCell","position":{"start":{"line":8,"column":1},"end":{"line":8,"column":1}},"children":[{"type":"text","value":"MAWT","position":{"start":{"line":8,"column":1},"end":{"line":8,"column":1}},"key":"V7vJbiYaT6"}],"key":"PfY3cdD2ij"},{"type":"tableCell","position":{"start":{"line":8,"column":1},"end":{"line":8,"column":1}},"children":[{"type":"text","value":"Maximum Allowable Working Temperature, the maximum temperature at which the vessel is permitted to operate","position":{"start":{"line":8,"column":1},"end":{"line":8,"column":1}},"key":"vnzcSJe2dq"}],"key":"tDJwTG7EuU"}],"key":"f47HpypNd0"},{"type":"tableRow","position":{"start":{"line":9,"column":1},"end":{"line":9,"column":1}},"children":[{"type":"tableCell","position":{"start":{"line":9,"column":1},"end":{"line":9,"column":1}},"children":[{"type":"text","value":"MDMT","position":{"start":{"line":9,"column":1},"end":{"line":9,"column":1}},"key":"oFumYJo940"}],"key":"DDsEYN0PkI"},{"type":"tableCell","position":{"start":{"line":9,"column":1},"end":{"line":9,"column":1}},"children":[{"type":"text","value":"Minimum Design Metal Temperature, the lowest temperature at which the vessel is permitted to operate","position":{"start":{"line":9,"column":1},"end":{"line":9,"column":1}},"key":"RN6AT1k1sW"}],"key":"oolOYzGYVD"}],"key":"vPPWGl9gAv"},{"type":"tableRow","position":{"start":{"line":10,"column":1},"end":{"line":10,"column":1}},"children":[{"type":"tableCell","position":{"start":{"line":10,"column":1},"end":{"line":10,"column":1}},"children":[{"type":"text","value":"Operating Pressure","position":{"start":{"line":10,"column":1},"end":{"line":10,"column":1}},"key":"BanX5dLZo3"}],"key":"gZItOirYHX"},{"type":"tableCell","position":{"start":{"line":10,"column":1},"end":{"line":10,"column":1}},"children":[{"type":"text","value":"The pressure at which the vessel is intended to operate; no more than 90% of the MAWP","position":{"start":{"line":10,"column":1},"end":{"line":10,"column":1}},"key":"vTugFjuxdJ"}],"key":"GKP8R1plLV"}],"key":"p2NzH8c0Om"},{"type":"tableRow","position":{"start":{"line":11,"column":1},"end":{"line":11,"column":1}},"children":[{"type":"tableCell","position":{"start":{"line":11,"column":1},"end":{"line":11,"column":1}},"children":[{"type":"text","value":"Accumulation","position":{"start":{"line":11,"column":1},"end":{"line":11,"column":1}},"key":"nJvylvIs7r"}],"key":"opHreno9QJ"},{"type":"tableCell","position":{"start":{"line":11,"column":1},"end":{"line":11,"column":1}},"children":[{"type":"text","value":"The pressure increase over the MAWP that occurs when the relief device is operating; expressed as a percentage of the MAWP","position":{"start":{"line":11,"column":1},"end":{"line":11,"column":1}},"key":"C05xerBfbV"}],"key":"ltPt9HTWte"}],"key":"PiPd7cxRHK"},{"type":"tableRow","position":{"start":{"line":12,"column":1},"end":{"line":12,"column":1}},"children":[{"type":"tableCell","position":{"start":{"line":12,"column":1},"end":{"line":12,"column":1}},"children":[{"type":"text","value":"Overpressure","position":{"start":{"line":12,"column":1},"end":{"line":12,"column":1}},"key":"Dgd7bOImEi"}],"key":"z2ZdFHOoBP"},{"type":"tableCell","position":{"start":{"line":12,"column":1},"end":{"line":12,"column":1}},"children":[{"type":"text","value":"The pressure increase over the set pressure that occurs when the relief device is operating; expressed as a percentage of the set pressure","position":{"start":{"line":12,"column":1},"end":{"line":12,"column":1}},"key":"JAB67zSh35"}],"key":"UaSZCgEmLk"}],"key":"bE9zj0Mq2P"},{"type":"tableRow","position":{"start":{"line":13,"column":1},"end":{"line":13,"column":1}},"children":[{"type":"tableCell","position":{"start":{"line":13,"column":1},"end":{"line":13,"column":1}},"children":[{"type":"text","value":"Back Pressure","position":{"start":{"line":13,"column":1},"end":{"line":13,"column":1}},"key":"fyZF00b9Hl"}],"key":"l9G7TwG385"},{"type":"tableCell","position":{"start":{"line":13,"column":1},"end":{"line":13,"column":1}},"children":[{"type":"text","value":"The pressure at the outlet of the relief device; composed of two components: pressure from downstream and pressure required for frictional losses","position":{"start":{"line":13,"column":1},"end":{"line":13,"column":1}},"key":"C65oqGqTtM"}],"key":"lnpwsxZM85"}],"key":"eYUbHtAkjY"},{"type":"tableRow","position":{"start":{"line":14,"column":1},"end":{"line":14,"column":1}},"children":[{"type":"tableCell","position":{"start":{"line":14,"column":1},"end":{"line":14,"column":1}},"children":[{"type":"text","value":"Blowdown","position":{"start":{"line":14,"column":1},"end":{"line":14,"column":1}},"key":"uokX245bVG"}],"key":"WMlzlvcLsP"},{"type":"tableCell","position":{"start":{"line":14,"column":1},"end":{"line":14,"column":1}},"children":[{"type":"text","value":"The difference between the set pressure and the relief reseating pressure","position":{"start":{"line":14,"column":1},"end":{"line":14,"column":1}},"key":"l4iAqD59UM"}],"key":"rYIaUUrvH7"}],"key":"CaUtwNWuhG"},{"type":"tableRow","position":{"start":{"line":15,"column":1},"end":{"line":15,"column":1}},"children":[{"type":"tableCell","position":{"start":{"line":15,"column":1},"end":{"line":15,"column":1}},"children":[{"type":"text","value":"Maximum allowable accumulation pressure","position":{"start":{"line":15,"column":1},"end":{"line":15,"column":1}},"key":"fjDzMP0mbT"}],"key":"o4IhthShCq"},{"type":"tableCell","position":{"start":{"line":15,"column":1},"end":{"line":15,"column":1}},"children":[{"type":"text","value":"Sum of the accumulation and the MAWP","position":{"start":{"line":15,"column":1},"end":{"line":15,"column":1}},"key":"EzozretNiR"}],"key":"wQzTPd7EzL"}],"key":"dHkmnDb3xK"},{"type":"tableRow","position":{"start":{"line":16,"column":1},"end":{"line":16,"column":1}},"children":[{"type":"tableCell","position":{"start":{"line":16,"column":1},"end":{"line":16,"column":1}},"children":[{"type":"text","value":"Relieving pressure","position":{"start":{"line":16,"column":1},"end":{"line":16,"column":1}},"key":"JDIOUNS0X3"}],"key":"UMo1L8sh70"},{"type":"tableCell","position":{"start":{"line":16,"column":1},"end":{"line":16,"column":1}},"children":[{"type":"text","value":"The pressure at which the relief device is fully open and relieving: set pressure plus overpressure","position":{"start":{"line":16,"column":1},"end":{"line":16,"column":1}},"key":"H4rXXI8iFN"}],"key":"JYefCxlCu3"}],"key":"z6FVvNSgqy"}],"key":"JWNSYmvfGU"}],"key":"sXUarCdx5p"},{"type":"block","kind":"notebook-content","children":[{"type":"paragraph","position":{"start":{"line":1,"column":1},"end":{"line":1,"column":1}},"children":[{"type":"text","value":"Code comments:","position":{"start":{"line":1,"column":1},"end":{"line":1,"column":1}},"key":"No1wvXxn7M"}],"key":"O3VrTJh6Ec"},{"type":"list","ordered":false,"spread":false,"position":{"start":{"line":3,"column":1},"end":{"line":10,"column":1}},"children":[{"type":"listItem","spread":true,"position":{"start":{"line":3,"column":1},"end":{"line":3,"column":1}},"children":[{"type":"text","value":"The maximum normal operating pressure can never exceed the MAWP, even momentarily.  However, the actual pressure during the relieving process may exceed the MAWP.","position":{"start":{"line":3,"column":1},"end":{"line":3,"column":1}},"key":"sXM7daaZY8"}],"key":"IpKWVSWw7C"},{"type":"listItem","spread":true,"position":{"start":{"line":4,"column":1},"end":{"line":4,"column":1}},"children":[{"type":"text","value":"Pressure tests (to verify strength) are often performed at 1.5 times the MAWP. Tests use water typically (gas tests would yield a much more violent failure if the vessel were to fail during the test).","position":{"start":{"line":4,"column":1},"end":{"line":4,"column":1}},"key":"xFazeZGilc"}],"key":"HI16enbzpq"},{"type":"listItem","spread":true,"position":{"start":{"line":5,"column":1},"end":{"line":5,"column":1}},"children":[{"type":"text","value":"For a single relief, the maximum set pressure is the MAWP.","position":{"start":{"line":5,"column":1},"end":{"line":5,"column":1}},"key":"y6xzvLblmz"}],"key":"eKA4JzzyjT"},{"type":"listItem","spread":true,"position":{"start":{"line":6,"column":1},"end":{"line":9,"column":1}},"children":[{"type":"text","value":"During the relieving process, the overpressure cannot exceed the MAWP by more than the following percentages:","position":{"start":{"line":6,"column":1},"end":{"line":6,"column":1}},"key":"EyRXtZuOeT"},{"type":"list","ordered":false,"spread":false,"position":{"start":{"line":7,"column":1},"end":{"line":9,"column":1}},"children":[{"type":"listItem","spread":true,"position":{"start":{"line":7,"column":1},"end":{"line":7,"column":1}},"children":[{"type":"text","value":"110% for vessels equipped with a single pressure relief device.","position":{"start":{"line":7,"column":1},"end":{"line":7,"column":1}},"key":"bk1Slr7IeD"}],"key":"bhnPqfKcRb"},{"type":"listItem","spread":true,"position":{"start":{"line":8,"column":1},"end":{"line":8,"column":1}},"children":[{"type":"text","value":"116% for vessels equipped with supplemental pressure relief devices.","position":{"start":{"line":8,"column":1},"end":{"line":8,"column":1}},"key":"IsCqmuVCNy"}],"key":"PJItBGw2Ng"},{"type":"listItem","spread":true,"position":{"start":{"line":9,"column":1},"end":{"line":9,"column":1}},"children":[{"type":"text","value":"121% for fire exposures.","position":{"start":{"line":9,"column":1},"end":{"line":9,"column":1}},"key":"xIAthdEmZF"}],"key":"Dtx04sRHDM"}],"key":"NbJ6UuVDMD"}],"key":"sxiTZAa3hK"},{"type":"listItem","spread":true,"position":{"start":{"line":10,"column":1},"end":{"line":10,"column":1}},"children":[{"type":"text","value":"For supplemental relief devices, the max. set pressure is 105% of the MAWP.","position":{"start":{"line":10,"column":1},"end":{"line":10,"column":1}},"key":"vJtI8R5EeN"}],"key":"OgB8GZgn4r"}],"key":"aNxZ6ZKmBH"}],"key":"wwA5Swcxpu"},{"type":"block","kind":"notebook-content","children":[{"type":"image","url":"/7407298d9ce3b29f077a008ded2cb7b6.png","width":500,"key":"pCUOwch96K","urlSource":"https://github.com/clint-bg/safetyinjc/blob/main/physical/supportfiles/PRV1.png?raw=true","urlOptimized":"/7407298d9ce3b29f077a008ded2cb7b6.webp"}],"key":"HuYl5mLU9P"},{"type":"block","kind":"notebook-content","children":[{"type":"image","url":"/5b8ac56b930f1ddf6ed7f372b9f87d6c.png","width":500,"key":"M2TRbLLfDi","urlSource":"https://github.com/clint-bg/safetyinjc/blob/main/physical/supportfiles/PRV2.png?raw=true","urlOptimized":"/5b8ac56b930f1ddf6ed7f372b9f87d6c.webp"}],"key":"nNAZdbh5a7"},{"type":"block","kind":"notebook-content","children":[{"type":"heading","depth":2,"position":{"start":{"line":1,"column":1},"end":{"line":1,"column":1}},"children":[{"type":"text","value":"Where and Why Pressure Protection Devices are Used","position":{"start":{"line":1,"column":1},"end":{"line":1,"column":1}},"key":"tZZ89Fh9h2"}],"identifier":"where-and-why-pressure-protection-devices-are-used","label":"Where and Why Pressure Protection Devices are Used","html_id":"where-and-why-pressure-protection-devices-are-used","implicit":true,"key":"QetgzIzJtN"}],"key":"IHAdzZ62t2"},{"type":"block","kind":"notebook-content","children":[{"type":"heading","depth":3,"position":{"start":{"line":1,"column":1},"end":{"line":1,"column":1}},"children":[{"type":"text","value":"Vessels","position":{"start":{"line":1,"column":1},"end":{"line":1,"column":1}},"key":"Wh4pSdhyum"}],"identifier":"vessels","label":"Vessels","html_id":"vessels","implicit":true,"key":"lbI7Ry3qpm"},{"type":"paragraph","position":{"start":{"line":2,"column":1},"end":{"line":2,"column":1}},"children":[{"type":"text","value":"All vessels, including reactors, storage tanks, heat exchangers, towers and drums.","position":{"start":{"line":2,"column":1},"end":{"line":2,"column":1}},"key":"cKZrWDeiL7"}],"key":"kvJf3tpNrS"}],"key":"R0At2AlYob"},{"type":"block","kind":"notebook-content","children":[{"type":"heading","depth":3,"position":{"start":{"line":1,"column":1},"end":{"line":1,"column":1}},"children":[{"type":"text","value":"Positive Displacement Pumps, Compressors, and Turbines","position":{"start":{"line":1,"column":1},"end":{"line":1,"column":1}},"key":"Ma6vfjKcQk"}],"identifier":"positive-displacement-pumps-compressors-and-turbines","label":"Positive Displacement Pumps, Compressors, and Turbines","html_id":"positive-displacement-pumps-compressors-and-turbines","implicit":true,"key":"QkdzaDPDx6"},{"type":"paragraph","position":{"start":{"line":2,"column":1},"end":{"line":2,"column":1}},"children":[{"type":"text","value":"These devices can be blocked in by a closed valve, causing the pressure to rise. These processing pieces may have an internal relief valve.","position":{"start":{"line":2,"column":1},"end":{"line":2,"column":1}},"key":"Ccs4Fcssqi"}],"key":"cxNKPtNlbh"}],"key":"p1x54kU4ji"},{"type":"block","kind":"notebook-content","children":[{"type":"heading","depth":3,"position":{"start":{"line":1,"column":1},"end":{"line":1,"column":1}},"children":[{"type":"text","value":"Piping","position":{"start":{"line":1,"column":1},"end":{"line":1,"column":1}},"key":"NQXngFme0i"}],"identifier":"piping","label":"Piping","html_id":"piping","implicit":true,"key":"rIbf3b9NMC"},{"type":"paragraph","position":{"start":{"line":3,"column":1},"end":{"line":3,"column":1}},"children":[{"type":"text","value":"Piping is not normally required or recommended to have pressure relief protection as piping can typically withstand pressures higher than the vessels they supply. However, there are some exceptions:","position":{"start":{"line":3,"column":1},"end":{"line":3,"column":1}},"key":"fffM9uJNAC"}],"key":"jQ4q7MyJzr"},{"type":"list","ordered":false,"spread":false,"position":{"start":{"line":5,"column":1},"end":{"line":11,"column":1}},"children":[{"type":"listItem","spread":true,"position":{"start":{"line":5,"column":1},"end":{"line":5,"column":1}},"children":[{"type":"text","value":"blocked-in sections of liquid-filled piping that may be heated or otherwise pressurized","position":{"start":{"line":5,"column":1},"end":{"line":5,"column":1}},"key":"VoPZtaYuEl"}],"key":"wzNdFttKee"},{"type":"listItem","spread":true,"position":{"start":{"line":6,"column":1},"end":{"line":6,"column":1}},"children":[{"type":"text","value":"heat traced piping","position":{"start":{"line":6,"column":1},"end":{"line":6,"column":1}},"key":"jiHjEeTCeg"}],"key":"jgwxGiFfoj"},{"type":"listItem","spread":true,"position":{"start":{"line":7,"column":1},"end":{"line":7,"column":1}},"children":[{"type":"text","value":"long lines (thermal expansion)","position":{"start":{"line":7,"column":1},"end":{"line":7,"column":1}},"key":"SwUjOIbo9s"}],"key":"iZ2L2FfYDz"},{"type":"listItem","spread":true,"position":{"start":{"line":8,"column":1},"end":{"line":8,"column":1}},"children":[{"type":"text","value":"loading or transfer lines beyond the property line","position":{"start":{"line":8,"column":1},"end":{"line":8,"column":1}},"key":"haXyJySJ7M"}],"key":"kG0Zsq466M"},{"type":"listItem","spread":true,"position":{"start":{"line":9,"column":1},"end":{"line":9,"column":1}},"children":[{"type":"text","value":"lines with history of overpressure","position":{"start":{"line":9,"column":1},"end":{"line":9,"column":1}},"key":"BcTPiXDECg"}],"key":"wG5rveRV6Q"},{"type":"listItem","spread":true,"position":{"start":{"line":10,"column":1},"end":{"line":10,"column":1}},"children":[{"type":"text","value":"lines that may be exposed to high pressures","position":{"start":{"line":10,"column":1},"end":{"line":10,"column":1}},"key":"xPnIoV4JFb"}],"key":"zQCVL3reLj"},{"type":"listItem","spread":true,"position":{"start":{"line":11,"column":1},"end":{"line":11,"column":1}},"children":[{"type":"text","value":"per the hazards analysis","position":{"start":{"line":11,"column":1},"end":{"line":11,"column":1}},"key":"JPyGzNhKBt"}],"key":"tTnttlkrkF"}],"key":"bwRsFSaf48"}],"key":"gJLA1WaEAe"},{"type":"block","kind":"notebook-content","children":[{"type":"heading","depth":3,"position":{"start":{"line":1,"column":1},"end":{"line":1,"column":1}},"children":[{"type":"text","value":"Examples of Where Pressure Protection Devices are Used","position":{"start":{"line":1,"column":1},"end":{"line":1,"column":1}},"key":"CpwYAGXvGK"}],"identifier":"examples-of-where-pressure-protection-devices-are-used","label":"Examples of Where Pressure Protection Devices are Used","html_id":"examples-of-where-pressure-protection-devices-are-used","implicit":true,"key":"vnWT7iF1qM"}],"key":"MNWRKHXLU9"},{"type":"block","kind":"notebook-content","children":[{"type":"image","url":"/3fc8f4c1f78e912e85c6ecef2e7bd7e9.png","width":600,"key":"nJy4GnxMh4","urlSource":"https://github.com/clint-bg/safetyinjc/blob/main/physical/supportfiles/reliefexample.png?raw=true","urlOptimized":"/3fc8f4c1f78e912e85c6ecef2e7bd7e9.webp"}],"key":"QCscEdYWGw"},{"type":"block","kind":"notebook-content","children":[{"type":"admonition","kind":"note","children":[{"type":"admonitionTitle","children":[{"type":"text","value":"Note","key":"DQiubOvMJd"}],"key":"roGl78rvUy"},{"type":"list","ordered":false,"spread":false,"position":{"start":{"line":2,"column":1},"end":{"line":7,"column":1}},"children":[{"type":"listItem","spread":true,"position":{"start":{"line":2,"column":1},"end":{"line":2,"column":1}},"children":[{"type":"text","value":"Blocked in heating coils.","position":{"start":{"line":2,"column":1},"end":{"line":2,"column":1}},"key":"JzzjOblunY"}],"key":"tB8OdsCBDs"},{"type":"listItem","spread":true,"position":{"start":{"line":3,"column":1},"end":{"line":3,"column":1}},"children":[{"type":"text","value":"Blocked in cooling water line on reflux condenser.","position":{"start":{"line":3,"column":1},"end":{"line":3,"column":1}},"key":"kGbDRDx0ZK"}],"key":"NrEA64qAE9"},{"type":"listItem","spread":true,"position":{"start":{"line":4,"column":1},"end":{"line":4,"column":1}},"children":[{"type":"text","value":"Relief on reactor  variety of scenarios.","position":{"start":{"line":4,"column":1},"end":{"line":4,"column":1}},"key":"sRdO12dW7E"}],"key":"eHNEWrEUFG"},{"type":"listItem","spread":true,"position":{"start":{"line":5,"column":1},"end":{"line":5,"column":1}},"children":[{"type":"text","value":"Relief on pump  need to check with manufacturer of pump.","position":{"start":{"line":5,"column":1},"end":{"line":5,"column":1}},"key":"mX4g86Urp7"}],"key":"TocQkePNbv"},{"type":"listItem","spread":true,"position":{"start":{"line":6,"column":1},"end":{"line":6,"column":1}},"children":[{"type":"text","value":"Side reaction? Incompatibility?","position":{"start":{"line":6,"column":1},"end":{"line":6,"column":1}},"key":"yG6dOb08JN"}],"key":"taR0krhpiE"},{"type":"listItem","spread":true,"position":{"start":{"line":7,"column":1},"end":{"line":7,"column":1}},"children":[{"type":"text","value":"Fire?","position":{"start":{"line":7,"column":1},"end":{"line":7,"column":1}},"key":"NGSLBxCsId"}],"key":"FOZRTuyBz8"}],"key":"aVQooLYSJE"}],"key":"t12UP7nRIA"}],"key":"yrMGbCmGyD"},{"type":"block","kind":"notebook-content","children":[{"type":"image","url":"/80262f991a4c153fd4b1c19d60de3716.png","width":600,"key":"WKgHB55hfV","urlSource":"https://github.com/clint-bg/safetyinjc/blob/main/physical/supportfiles/reliefexample2.png?raw=true","urlOptimized":"/80262f991a4c153fd4b1c19d60de3716.webp"}],"key":"k2gk5Rskmq"},{"type":"block","kind":"notebook-content","children":[{"type":"admonition","kind":"note","children":[{"type":"admonitionTitle","children":[{"type":"text","value":"Note","key":"nCUhtJcC3L"}],"key":"oiX9fbiQ2P"},{"type":"list","ordered":false,"spread":false,"position":{"start":{"line":2,"column":1},"end":{"line":7,"column":1}},"children":[{"type":"listItem","spread":true,"position":{"start":{"line":2,"column":1},"end":{"line":2,"column":1}},"children":[{"type":"text","value":"Failure of high pressure nitrogen regulator","position":{"start":{"line":2,"column":1},"end":{"line":2,"column":1}},"key":"PwSgi9DQMJ"}],"key":"abbfgKmFch"},{"type":"listItem","spread":true,"position":{"start":{"line":3,"column":1},"end":{"line":3,"column":1}},"children":[{"type":"text","value":"Hole in cooling water coil.","position":{"start":{"line":3,"column":1},"end":{"line":3,"column":1}},"key":"QqSlMAyX4h"}],"key":"D0lSBlqUFv"},{"type":"listItem","spread":true,"position":{"start":{"line":4,"column":1},"end":{"line":4,"column":1}},"children":[{"type":"text","value":"Pump continues to run after filling.","position":{"start":{"line":4,"column":1},"end":{"line":4,"column":1}},"key":"vff2yHa2jl"}],"key":"eCmqNsFaHN"},{"type":"listItem","spread":true,"position":{"start":{"line":5,"column":1},"end":{"line":5,"column":1}},"children":[{"type":"text","value":"Fire exposure","position":{"start":{"line":5,"column":1},"end":{"line":5,"column":1}},"key":"iNwIAMTgNh"}],"key":"GplLFvrsex"},{"type":"listItem","spread":true,"position":{"start":{"line":6,"column":1},"end":{"line":6,"column":1}},"children":[{"type":"text","value":"Runaway reaction","position":{"start":{"line":6,"column":1},"end":{"line":6,"column":1}},"key":"aaHWTulwsQ"}],"key":"jumPUCiU8O"},{"type":"listItem","spread":true,"position":{"start":{"line":7,"column":1},"end":{"line":7,"column":1}},"children":[{"type":"text","value":"Blocked outlet","position":{"start":{"line":7,"column":1},"end":{"line":7,"column":1}},"key":"NCjkbqUY1a"}],"key":"eZdYV3AcJO"}],"key":"dPqgJiKRjW"}],"key":"AIIpxKdSzf"}],"key":"ve3dTj6VbV"},{"type":"block","kind":"notebook-content","children":[{"type":"image","url":"/eb2b283f58a98e88a09bbc239b926de2.png","width":500,"key":"yyQpepyKZr","urlSource":"https://github.com/clint-bg/safetyinjc/blob/main/physical/supportfiles/WherePRV.png?raw=true","urlOptimized":"/eb2b283f58a98e88a09bbc239b926de2.webp"},{"type":"paragraph","position":{"start":{"line":3,"column":1},"end":{"line":3,"column":1}},"children":[{"type":"text","value":"*Source: Crowl and Louvar, Chemical Process Safety, 4th Edition, FIgure 9-8.","position":{"start":{"line":3,"column":1},"end":{"line":3,"column":1}},"key":"z4O7MoVbJu"}],"key":"L3xKzFlZLF"}],"key":"UFlZGpLNTb"},{"type":"block","kind":"notebook-content","children":[{"type":"heading","depth":2,"position":{"start":{"line":1,"column":1},"end":{"line":1,"column":1}},"children":[{"type":"text","value":"Relief Effluent Handling","position":{"start":{"line":1,"column":1},"end":{"line":1,"column":1}},"key":"sR0ngXeXNv"}],"identifier":"relief-effluent-handling","label":"Relief Effluent Handling","html_id":"relief-effluent-handling","implicit":true,"key":"y7waxbozRC"}],"key":"dUPvAZFsaw"},{"type":"block","kind":"notebook-content","children":[{"type":"paragraph","position":{"start":{"line":1,"column":1},"end":{"line":1,"column":1}},"children":[{"type":"text","value":"Oft times, the relief effluent cannot simply be released to the atmosphere. The effluent may be toxic, flammable, or otherwise hazardous. The effluent may also be at a high temperature or pressure. Some options for handling the effluent include:","position":{"start":{"line":1,"column":1},"end":{"line":1,"column":1}},"key":"oZKQsqGfy5"}],"key":"XMj00lrygQ"},{"type":"list","ordered":false,"spread":false,"position":{"start":{"line":3,"column":1},"end":{"line":7,"column":1}},"children":[{"type":"listItem","spread":true,"position":{"start":{"line":3,"column":1},"end":{"line":3,"column":1}},"children":[{"type":"text","value":"Flare","position":{"start":{"line":3,"column":1},"end":{"line":3,"column":1}},"key":"cTGde4cTNI"}],"key":"jNHPMdGbSN"},{"type":"listItem","spread":true,"position":{"start":{"line":4,"column":1},"end":{"line":4,"column":1}},"children":[{"type":"text","value":"Vent to a scrubber","position":{"start":{"line":4,"column":1},"end":{"line":4,"column":1}},"key":"kp9QKeD5Qy"}],"key":"jXymZFii5Z"},{"type":"listItem","spread":true,"position":{"start":{"line":5,"column":1},"end":{"line":5,"column":1}},"children":[{"type":"text","value":"Vent to a thermal oxidizer","position":{"start":{"line":5,"column":1},"end":{"line":5,"column":1}},"key":"qbmHs8nJ44"}],"key":"OaIBiWnHHV"},{"type":"listItem","spread":true,"position":{"start":{"line":6,"column":1},"end":{"line":6,"column":1}},"children":[{"type":"text","value":"Vent to a condenser","position":{"start":{"line":6,"column":1},"end":{"line":6,"column":1}},"key":"fV4jCmiUJq"}],"key":"ebWcttaRGG"},{"type":"listItem","spread":true,"position":{"start":{"line":7,"column":1},"end":{"line":7,"column":1}},"children":[{"type":"text","value":"Vent to a knock-out drum","position":{"start":{"line":7,"column":1},"end":{"line":7,"column":1}},"key":"CTKWiDnm0C"}],"key":"IId5UoTDl3"}],"key":"ew4AKZUqvJ"}],"key":"x0XTIzD6QX"}],"key":"sVf1shfZ5Q"},"references":{"cite":{"order":[],"data":{}}}}